gti/app.py
gti/gti.png
GolfGTI-1.1.1.dist-info/LICENSE
GolfGTI-1.1.1.dist-info/METADATA
GolfGTI-1.1.1.dist-info/WHEEL
GolfGTI-1.1.1.dist-info/entry_points.txt
GolfGTI-1.1.1.dist-info/top_level.txt
GolfGTI-1.1.1.dist-info/RECORD
